{
	"name": "Наборы улучшений",
	"category": "assemblylinemachines:items",
	"icon": "assemblylinemachines:electric_upgrade_kit",
	"pages": [
		{
			"type": "text",
			"text": "Если вам понадобиться массово улучшать все свои механизмы, необязательно их ломать и улучшать на верстаке. Попробуйте использовать $(1)Набор улучшений.$() Надо всего лишь нажать подобным Shift+ПКМ по механизму и он улучшится, сохранив всё, что было внутри!"
		},
		{
			"type": "crafting",
			"recipe": "assemblylinemachines:crafting/electric_upgrade_kit",
			"text": "$(4)Набор улучшений \"Электроника\"$() превращает Кинетические механизмы в соответствующие Электрические вариации."
		},
		{
			"type": "crafting",
			"recipe": "assemblylinemachines:crafting/mkii_upgrade_kit",
			"text": "$(9)Набор улучшений MkII$() превращает любую Электрическую машину в её MkII версию, сохраняя все установленные улучшения. Кроме того, все текущие рецепты будут помещены в ПЕРВЫЙ канал."
		}
	]
}